[{"name":"Lingala Pavan Kumar","number":"9000875047","password":"$2y$10$6OO\/C8q2lngPYxpzZ9GNSOySYu4YHRrIIOCNs4MPUHoedSIGEQdlS","balance":65.75999999999999,"email":"pk5585123@gmail.com","phone":"9000875047","reset_code":"6791b76db64f7","logo":"uploads\/profile_logos\/67a557efc2afc-1000425590.png","reset_token":"18c821b60a2666bf8914d89167605474c15554aab4bbfe4ff6bf527aa92dd186","token_expiry":"2025-01-23 17:16:05","telegram_id":"6355858089"},{"name":"Sai","number":"123456","password":"$2y$10$ToWuBReU79HiwaT9MRZ7serg5eG.6u2UIknFEU4YrmoIQ1r6MsZFC","balance":1},{"name":"Chingri","number":"6000490920","password":"$2y$10$lDzZVZWp6CeE8g7CgxiPH.nvk0WuUgc1TlmKntGwxcBQub6kH9zuS","balance":6},{"name":"Dev","number":"9656308588","password":"$2y$10$ZUC444kyag2tZxwJz8ysf.QVTUWCP0cmOFySpXmCTPb9KLYUXfcMm","balance":4},{"name":"Jayesh","number":"1324132400","password":"$2y$10$dM6lhmnbN9p\/zBG0EEXxO.MBPpkxHr38QKwOBnwN5U.HLwxJ64.Je","balance":1},{"name":"Pawan","number":"8080486169","password":"$2y$10$zZ3tPuczz.jOGTPocMXYAuerfNMorZQw3YeJpn8n0094F1qbydVcK","balance":1},{"name":"Vashu Chauhan","number":"7668653740","password":"$2y$10$Uo2MJfLZshN0vhpMmiN1NOCTH7M\/3HZ7DKXBXsXUH2.bCfLAlhCri","balance":6},{"name":"Siamislam","number":"01324044683","password":"$2y$10$Es5Q3jlKHP2UTuicvZdCnOnUfeJoGeVbSFASZC9lOkMGZ.jsZ5Df2","balance":1},{"name":"Mohamed ","number":"9400814059","password":"$2y$10$wXMNAL1qxx5LHvLs.rah2.u1tW6PF6aft4s3vY\/kmN7QyDb8aYOyO","balance":1},{"name":"Shuvamoy","number":"7679659729","password":"$2y$10$wyougPpCzK9m7X71neQre.uPfKN2Ayd.u\/3BkLLyRkJenydXAHdg2","balance":0},{"name":"jitu","number":"8591183301","password":"$2y$10$8yuN5ILNuvUUQ3g5dUgy4ucQw0MpGEimqEn7jFzHMgzqOD\/ZoyRGS","balance":0},{"name":"Nishant ","number":"8651875778","password":"$2y$10$VB3C3PMv2COU585lWASOT.x87MyhIH5xoLQZquJ\/ZcsTCtWD3d0Su","balance":5},{"name":"Raihankhan","number":"7085153327","password":"$2y$10$FTGQ5q8LWKoGSVw.I9334OgYW1JcjR.I4PKHP1JnFuzbt5W92LhpK","balance":0},{"name":"Vishal yadav","number":"9887640432","password":"$2y$10$HkvyTgl7H7pzDHrSKhIx3uCHigpnzG1OlmVlR2xmPIYFKAWZ4mliW","balance":5},{"name":"Satyam","number":"7052794282","password":"$2y$10$Fm9l6CxrVBCc0TnpYJv\/GORz193gGxkL04YP2unT6B\/2m1oP5SZmC","balance":0},{"name":"Raihankhan","number":"7085153627","password":"$2y$10$DXKbah4oP2YcTrX7g2X3we79bNcdTQJrBDDTlKp6Bk0neYgX9GktS","balance":5},{"name":"Moinkhan","number":"8188951093","password":"$2y$10$RDQn0mNio1aXLWaI5Sn55OjgGi.4fN3Pc.1hqFcTXfhb.FovUiaTC","balance":0},{"name":"Soniya","number":"9864997952","password":"$2y$10$mDeKWvflRMt7kCNY\/YzBg.jXkl7jXDE28nxTVLq0hO6OKENgnavWS","balance":5},{"name":"Vedant2008","number":"6392530600","password":"$2y$10$VC\/wkV6VkpMaNAoS1P37cOF53dd3uuWLBHPjGru.7DmNfnknWxgQ2","balance":5},{"name":"Rajesh ","number":"9949031065","password":"$2y$10$vWO8KvTSwvYSqPUNDCtRCeuGpcEh7ZJExl33BC3fpsoVY\/Aw\/LrbC","balance":0},{"name":"Sumit ","number":"9076564341","password":"$2y$10$HJHLueApJC\/P.3Aye1xtBOTaW\/q0Mm0deZiFStckxiH9xDl\/UXnXW","balance":5},{"name":"Shiva","number":"9528035185","password":"$2y$10$pUxJaqCf56KBp.k85dJT\/OwNpOcUUDDFXEugKUutOSYyHJzpitkaq","balance":0},{"name":"Tejas Chavan","number":"9370424028","password":"$2y$10$n9ra3u5Ge356dCT7T6ChROFhDD6qKW4R509A0b3wjm4R4w4k9WTdC","balance":0},{"name":"Rao ji","number":"8580856669","password":"$2y$10$kDTz\/\/XEPqcaf4WegynR1OEhndYt6Wnto7\/4zIYwuSv79Yggepi0O","balance":5},{"name":"Babu","number":"8099088425","password":"$2y$10$jpReVJIh7y4jUf0umQxxxeHctULqj4yBteARWxJ.zAMlgQxsaxOHq","balance":0},{"name":"Rahul","number":"6389795866","password":"$2y$10$lIuolFt009UdXRzNQGllXuEatCgk7KncItZUr8ey7zQP0CBymsA5u","balance":5},{"name":"Nishid Naidu ","number":"9326359204","password":"$2y$10$\/ZDf5InYf.18kpC2G1Gam.Sy8eLdoN.vx2jJnR9T4LM5pm5s6ouS6","balance":0},{"name":"Deepak","number":"9050636649","password":"$2y$10$14IgUvcguFCmR9K13o4.puWtg1.hWzamaJYDT1GrP7XMxA0J8wyUW","balance":5},{"name":"RAVI KUMAR","number":"8709477679","password":"$2y$10$iNMjzkKkjEC.qqIFPCM61O6lGXS1YtB6GEqUPb2YtZZMQ55UEmWxe","balance":5},{"name":"Krishna das ","number":"6001411773","password":"$2y$10$9xag8EG\/BSj8u7eATpXSIOmIMVdSiCmkMMKtisO8udB40MCA05VrO","balance":15},{"name":"Rohit ","number":"9893412213","password":"$2y$10$Ccq8J\/lQuYdpi5VIw4cvmOJPEVHJD2z4qSg8VPKl50ugR.c2HoDYm","balance":0},{"name":"Anmol","number":"7906693183","password":"$2y$10$eQm\/e2ytLjxd7SY.UdvTdexiN4LSqfZQq4iPZWXPE.W19zX.b7JnC","balance":0},{"name":"Satyajit ","number":"9954820247","password":"$2y$10$OXNs0dPaMTRb0voRZgxRKu3kJEA4wx8.fCp8L\/Yg2i0ukVVnTRsOq","balance":0},{"name":"Biswajit","number":"9395110950","password":"$2y$10$JarZSFZaEY7C\/zt2x.QoNujTftI3WvmMMhKYwSC.hZ9jUPXPvrEY.","balance":0},{"name":"Narayan das","number":"9365741934","password":"$2y$10$JBXhCC5EiocgTVWiv39eAOmklU.EqjV13qYR0twtDopWhBRwwd2dO","balance":0},{"name":"Ratul ","number":"6003536979","password":"$2y$10$HCSfCntq\/bILoZxlHRq5kOFLPszuML9Ad57ayygIFtpVFffGqjnI.","balance":1},{"name":"Manjit","number":"6001144128","password":"$2y$10$STzrKHOwCUfhY8B4utTfsuMszXA5KbdjZ9AbvkFxWb8WGKw7JXTLS","balance":0},{"name":"Gokul","number":"6000781305","password":"$2y$10$EFdFVpErMk.12cIfODZmCud9EinOUU9t00WQtBX0cUxGknW7zDbFe","balance":0},{"name":"Rina","number":"6003536972","password":"$2y$10$WDqk8xibfEa4rsDvtWIVc.lFK5I46\/WaF5Jlmu3SIkLZBgGt4KkY.","balance":0},{"name":"Mahadev","number":"9395110952","password":"$2y$10$0wEWKGYbacRv0CvylnQZfupa\/brdkFrLXmG5Rzpzy1mWOjjbDgl06","balance":0},{"name":"Hites","number":"9954820243","password":"$2y$10$3M2Y\/U69dNZsi0f17h1P6emnOSRD0dyf7eUXtChXYFPblSACTIlTK","balance":0},{"name":"Ak","number":"9110139530","password":"$2y$10$1iHtu\/lqMR8jIai5LGcLF.7T7Crh.RgVCJcHrwI678JGTjP14COE2","balance":0},{"name":"Jyotirmay roy","number":"9749994001","password":"$2y$10$kJ6GALLHP40dfuHyFjEFAO7OCXliaGEWVJo56KxJMgjyiBsoDFjZi","balance":5},{"name":"9575403379","number":"9575403379","password":"$2y$10$yTCVE4fFP.\/yus1kqnSOpOkpnwPsiV2cii5pbz91cfx3l13kYhRyK","balance":0},{"name":"Iam hacker","number":"9797763148","password":"$2y$10$AFR5.SaTSreDsTuKJvAj6OBROHhe2Ir2ePuEHluIRhQ1gTWq\/lLsG","balance":5},{"name":"Lingala Yogeshwara","number":"8688799729","password":"$2y$10$PmX2ewjLcPJaVoV1jkI2t.8YDAa8WyMlKXJSTnOu8Hk3YXBPU8eUy","balance":60.24},{"name":"9537273848","number":"9537273848","password":"$2y$10$.mLXDOnNJVIIKiMLmZtNBOLGcG6SASX4EtKD7pfFVzfq3YmhBvmd2","balance":0},{"name":"Yash","number":"8421658514","password":"$2y$10$ytO70QIx\/tL3cgYAHgUeteGSDzrW99PHL1KiF8tvZsvV3jFVk.hoy","balance":5},{"name":"Lofita","number":"0975623984","password":"$2y$10$JTKBMDXFcKjv\/PVsaGkLneB7UULbtbit9VRNc73YK78PC4DKTSs1S","balance":0},{"name":"Lofita","number":"0983999777","password":"$2y$10$3JID.fqyi3LMkBHJgF7Gger7CGQBs\/TwwnppaMFKA1ekcRa3vSgXy","balance":0},{"name":"Md wali ","number":"8862886488","password":"$2y$10$z.8nCPCAjkUN8HfDqyz9Zenu7uv.tpCXueWkzbc0brmMb6ZuBJoBq","balance":5},{"name":"Pawan","number":"9067150788","password":"$2y$10$xSyS9N3Qa3ajW91yyQwLgulgdywmb1JKxYTeNaRUf8ULpBah5mz22","balance":5},{"name":"Lovejot","number":"7009925064","password":"$2y$10$0NWzOmoLTU66XlASNbOgcO3XeEE\/vDeaEMIIZh3brJ8iyplM87Ooi","balance":0},{"name":"Sadikul Islam ","number":"6002728565","password":"$2y$10$1v86\/WMcgRQrKtLD5zWb2.dHgFsMrLBZoF4FxtK.iCFWH\/pVkZtNG","balance":0},{"name":"Roni Mitra","number":"7980110265","password":"$2y$10$L7GyUGxmf0cp7ztoNpUC5uADSigGhxOtOoiAX1xWd2G\/WW6\/rqDLa","balance":0}]
